django_htmx_refresh/__init__.py
django_htmx_refresh/admin.py
django_htmx_refresh/apps.py
django_htmx_refresh/middleware.py
django_htmx_refresh/mixins.py
django_htmx_refresh/migrations/__init__.py
django_htmx_refresh/tests/__init__.py
django_htmx_refresh-0.0.7.dist-info/LICENSE
django_htmx_refresh-0.0.7.dist-info/METADATA
django_htmx_refresh-0.0.7.dist-info/WHEEL
django_htmx_refresh-0.0.7.dist-info/top_level.txt
django_htmx_refresh-0.0.7.dist-info/RECORD
